{
  "title": "The Human Eye and",
  "outline": [
    {
      "level": "H1",
      "text": "The Human Eye and",
      "page": 1
    },
    {
      "level": "H1",
      "text": "the Colourful World",
      "page": 1
    },
    {
      "level": "H3",
      "text": "CHAPTER",
      "page": 1
    },
    {
      "level": "H4",
      "text": "10.1 THE HUMAN EYE",
      "page": 1
    },
    {
      "level": "H4",
      "text": "10.1.1 Power of Accommodation",
      "page": 2
    },
    {
      "level": "H4",
      "text": "10.2 DEFECTS OF VISION AND THEIR CORRECTION",
      "page": 2
    },
    {
      "level": "H4",
      "text": "10.2 DEFECTS OF VISION AND THEIR CORRECTION",
      "page": 2
    },
    {
      "level": "H4",
      "text": "10.2 DEFECTS OF VISION AND THEIR CORRECTION",
      "page": 2
    },
    {
      "level": "H4",
      "text": "10.2 DEFECTS OF VISION AND THEIR CORRECTION",
      "page": 2
    },
    {
      "level": "H4",
      "text": "10.2 DEFECTS OF VISION AND THEIR CORRECTION",
      "page": 2
    },
    {
      "level": "H4",
      "text": "10.3 REFRACTION OF LIGHT THROUGH A PRISM",
      "page": 5
    },
    {
      "level": "H4",
      "text": "10.3 REFRACTION OF LIGHT THROUGH A PRISM",
      "page": 5
    },
    {
      "level": "H4",
      "text": "10.3 REFRACTION OF LIGHT THROUGH A PRISM",
      "page": 5
    },
    {
      "level": "H4",
      "text": "10.3 REFRACTION OF LIGHT THROUGH A PRISM",
      "page": 5
    },
    {
      "level": "H4",
      "text": "10.3 REFRACTION OF LIGHT THROUGH A PRISM",
      "page": 5
    },
    {
      "level": "H4",
      "text": "Activity 10.1",
      "page": 5
    },
    {
      "level": "H4",
      "text": "Activity 10.1",
      "page": 5
    },
    {
      "level": "H4",
      "text": "Activity 10.1",
      "page": 5
    },
    {
      "level": "H4",
      "text": "Activity 10.1",
      "page": 5
    },
    {
      "level": "H4",
      "text": "Activity 10.1",
      "page": 5
    },
    {
      "level": "H4",
      "text": "Activity 10.2",
      "page": 6
    },
    {
      "level": "H4",
      "text": "Activity 10.2",
      "page": 6
    },
    {
      "level": "H4",
      "text": "Activity 10.2",
      "page": 6
    },
    {
      "level": "H4",
      "text": "Activity 10.2",
      "page": 6
    },
    {
      "level": "H4",
      "text": "Activity 10.2",
      "page": 6
    },
    {
      "level": "H4",
      "text": "10.4 DISPERSION OF WHITE LIGHT BY A GL",
      "page": 6
    },
    {
      "level": "H4",
      "text": "10.4 DISPERSION OF WHITE LIGHT BY A GL",
      "page": 6
    },
    {
      "level": "H4",
      "text": "10.4 DISPERSION OF WHITE LIGHT BY A GL",
      "page": 6
    },
    {
      "level": "H4",
      "text": "10.4 DISPERSION OF WHITE LIGHT BY A GL",
      "page": 6
    },
    {
      "level": "H4",
      "text": "10.4 DISPERSION OF WHITE LIGHT BY A GLASS PRISM",
      "page": 6
    },
    {
      "level": "H4",
      "text": "ASS PRISM",
      "page": 6
    },
    {
      "level": "H4",
      "text": "ASS PRISM",
      "page": 6
    },
    {
      "level": "H4",
      "text": "ASS PRISM",
      "page": 6
    },
    {
      "level": "H4",
      "text": "ASS PRISM",
      "page": 6
    },
    {
      "level": "H4",
      "text": "10.5 ATMOSPHERIC REFRACTION",
      "page": 8
    },
    {
      "level": "H4",
      "text": "10.6  SCATTERING OF LIGHT",
      "page": 9
    },
    {
      "level": "H4",
      "text": "10.6.1 Tyndall Effect",
      "page": 9
    },
    {
      "level": "H4",
      "text": "10.6.2 Why is the colour of the clear Sky Blue?",
      "page": 9
    },
    {
      "level": "H2",
      "text": "What you have learnt",
      "page": 10
    }
  ]
}